make_post_sell/__init__.py
make_post_sell/config_jinja2.py
make_post_sell/request_methods.py
make_post_sell/routes.py
make_post_sell/lib/__init__.py
make_post_sell/lib/currency.py
make_post_sell/lib/hex_color.py
make_post_sell/lib/mail.py
make_post_sell/lib/mail_messages.py
make_post_sell/lib/monero_address.py
make_post_sell/lib/phone_numbers.py
make_post_sell/lib/render.py
make_post_sell/lib/sanitize_html.py
make_post_sell/lib/time_funcs.py
make_post_sell/lib/uuid_validation.py
make_post_sell/lib/crypto_watcher/__init__.py
make_post_sell/lib/crypto_watcher/crypto_clients.py
make_post_sell/lib/crypto_watcher/crypto_payment_rescue.py
make_post_sell/models/__init__.py
make_post_sell/models/cart.py
make_post_sell/models/cart_coupon.py
make_post_sell/models/comment.py
make_post_sell/models/coupon.py
make_post_sell/models/coupon_redemption.py
make_post_sell/models/crypto_payment.py
make_post_sell/models/crypto_processor.py
make_post_sell/models/inventory.py
make_post_sell/models/invoice.py
make_post_sell/models/market.py
make_post_sell/models/meta.py
make_post_sell/models/paypal_user_shop.py
make_post_sell/models/price.py
make_post_sell/models/product.py
make_post_sell/models/shop.py
make_post_sell/models/shop_location.py
make_post_sell/models/shop_search_request.py
make_post_sell/models/stripe_user_shop.py
make_post_sell/models/user.py
make_post_sell/models/user_address.py
make_post_sell/models/user_crypto_refund_address.py
make_post_sell/models/user_product.py
make_post_sell/models/user_shop.py
make_post_sell/scripts/__init__.py
make_post_sell/scripts/fix_s3_acls.py
make_post_sell/scripts/initialize_db.py
make_post_sell/scripts/pshell.py
make_post_sell/scripts/alembic/env.py
make_post_sell/scripts/alembic/script.py.mako
make_post_sell/scripts/alembic/versions/03292288a132_role_id_to_user_shop_table.py
make_post_sell/scripts/alembic/versions/07908c8c840d_add_email_tracking_columns_to_crypto_.py
make_post_sell-1.1.5.dist-info/METADATA
make_post_sell-1.1.5.dist-info/WHEEL
make_post_sell-1.1.5.dist-info/entry_points.txt
make_post_sell-1.1.5.dist-info/top_level.txt
make_post_sell-1.1.5.dist-info/RECORD
