Metadata-Version: 2.4
Name: make_post_sell
Version: 1.1.5
Summary: Make Post Sell
Home-page: https://www.makepostsell.com
Author: Russell Ballestrini
Author-email: russell@ballestrini.net
Keywords: make post sell web pyramid pylons ecommerce digital downloads physical goods content marketing youtube alternative
Classifier: Programming Language :: Python :: 3
Classifier: Programming Language :: Python :: 3.6
Classifier: Programming Language :: Python :: 3.7
Classifier: Programming Language :: Python :: 3.8
Classifier: Programming Language :: Python :: 3.9
Classifier: Programming Language :: Python :: 3.10
Classifier: Programming Language :: Python :: 3.11
Classifier: Programming Language :: Python :: 3.12
Classifier: Programming Language :: Python :: 3.13
Classifier: Programming Language :: Python :: 3.14
Classifier: Programming Language :: Python :: 3.15
Classifier: Programming Language :: Python
Classifier: Framework :: Pyramid
Classifier: Topic :: Internet :: WWW/HTTP
Classifier: Topic :: Internet :: WWW/HTTP :: WSGI :: Application
Requires-Dist: six
Requires-Dist: plaster_pastedeploy
Requires-Dist: pyramid
Requires-Dist: pyramid_jinja2
Requires-Dist: pyramid_debugtoolbar
Requires-Dist: waitress
Requires-Dist: pyramid_retry
Requires-Dist: pyramid_tm
Requires-Dist: SQLAlchemy
Requires-Dist: SQLAlchemy-Utils
Requires-Dist: transaction
Requires-Dist: zope.sqlalchemy
Requires-Dist: alembic
Requires-Dist: boto3
Requires-Dist: python-slugify
Requires-Dist: bcrypt
Requires-Dist: stripe
Requires-Dist: paypalrestsdk
Requires-Dist: Adyen
Requires-Dist: dkimpy
Requires-Dist: dkimpy[ed25519]
Requires-Dist: markdown
Requires-Dist: ago
Requires-Dist: miniuri
Requires-Dist: bleach>=2.1.4
Requires-Dist: bleach-allowlist
Requires-Dist: beautifulsoup4
Requires-Dist: html5lib
Provides-Extra: dev
Requires-Dist: bpython; extra == "dev"
Requires-Dist: pyramid_bpython; extra == "dev"
Requires-Dist: waitress; extra == "dev"
Provides-Extra: prod
Requires-Dist: uwsgi; extra == "prod"
Requires-Dist: psycopg2; extra == "prod"
Provides-Extra: test
Requires-Dist: pytest; extra == "test"
Requires-Dist: pytest-cov; extra == "test"
Requires-Dist: nose; extra == "test"
Requires-Dist: mock; extra == "test"
Requires-Dist: WebTest; extra == "test"
Requires-Dist: fakeredis; extra == "test"
Dynamic: author
Dynamic: author-email
Dynamic: classifier
Dynamic: description
Dynamic: home-page
Dynamic: keywords
Dynamic: provides-extra
Dynamic: requires-dist
Dynamic: summary
